MANIFEST.in
README.rst
setup.py
robpol86_sphinxcontrib_googleanalytics.egg-info/PKG-INFO
robpol86_sphinxcontrib_googleanalytics.egg-info/SOURCES.txt
robpol86_sphinxcontrib_googleanalytics.egg-info/dependency_links.txt
robpol86_sphinxcontrib_googleanalytics.egg-info/namespace_packages.txt
robpol86_sphinxcontrib_googleanalytics.egg-info/not-zip-safe
robpol86_sphinxcontrib_googleanalytics.egg-info/requires.txt
robpol86_sphinxcontrib_googleanalytics.egg-info/top_level.txt
sphinxcontrib/__init__.py
sphinxcontrib/googleanalytics.py