Metadata-Version: 1.1
Name: robpol86-sphinxcontrib-googleanalytics
Version: 0.1
Summary: Sphinx extension googleanalytics
Home-page: http://bitbucket.org/birkenfeld/sphinx-contrib
Author: Domen Kozar
Author-email: domen@dev.si
License: BSD
Download-URL: http://pypi.python.org/pypi/sphinxcontrib-googleanalytics
Platform: any
Classifier: Development Status :: 4 - Beta
Classifier: Environment :: Console
Classifier: Environment :: Web Environment
Classifier: Intended Audience :: Developers
Classifier: License :: OSI Approved :: BSD License
Classifier: Operating System :: OS Independent
Classifier: Programming Language :: Python
Classifier: Topic :: Documentation
Classifier: Topic :: Utilities
